[
  {
    "name": "hdudud383/CraxsRAT-Official",
    "clone_url": "https://github.com/hdudud383/CraxsRAT-Official.git",
    "stars": 135,
    "size": 604
  },
  {
    "name": "weijunext/image-url-converter",
    "clone_url": "https://github.com/weijunext/image-url-converter.git",
    "stars": 80,
    "size": 370
  },
  {
    "name": "skydoves/flow-operators",
    "clone_url": "https://github.com/skydoves/flow-operators.git",
    "stars": 54,
    "size": 136
  },
  {
    "name": "Cere-Labs/maia",
    "clone_url": "https://github.com/Cere-Labs/maia.git",
    "stars": 48,
    "size": 4425
  },
  {
    "name": "amanvirparhar/elara",
    "clone_url": "https://github.com/amanvirparhar/elara.git",
    "stars": 47,
    "size": 83
  }
]